tess_sip/__init__.py
tess_sip/tess_sip.py
tess_sip-1.1.1.dist-info/LICENSE
tess_sip-1.1.1.dist-info/WHEEL
tess_sip-1.1.1.dist-info/METADATA
tess_sip-1.1.1.dist-info/RECORD
