Metadata-Version: 2.1
Name: tess-sip
Version: 1.1.1
Summary: Demo tool for creating a Systematics-insensitive Periodogram (SIP) to detect long period rotation in NASA's TESS mission data.
License: MIT
Keywords: NASA, TESS, Astronomy
Author: Christina Hedges
Author-email: christina.l.hedges@nasa.gov
Requires-Python: >=3.6.1,<4.0.0
Classifier: License :: OSI Approved :: MIT License
Classifier: Programming Language :: Python :: 3
Classifier: Programming Language :: Python :: 3.7
Classifier: Programming Language :: Python :: 3.8
Classifier: Programming Language :: Python :: 3.9
Requires-Dist: astropy (>3.2.3)
Requires-Dist: lightkurve (>=2.0.4)
Requires-Dist: numpy (>1.18.2)
Requires-Dist: scipy (>1.5.3)
Requires-Dist: tqdm (>4.41.1)
